{ 
    "vision":{

        "model_pars": {
            "model_name":"vision",
             "model_pars":{
                            "num_classes": null,
                            "multi_label": false,
                            "loss":  null,
                            "metrics": null,
                            "name":"vision_classifier",
                            "max_trials":10,
                            "directory": null,
                            "objective": "val_loss",
                            "overwrite":true,
                            "seed": null
                            }
        },

        "data_pars" :{
            "dataset": "MNIST",
            "data_path": "dataset/vision/",
            "validation_split":0.2
        },

        "compute_pars": {
            "epochs":2
        },

        "out_pars": {
            "checkpointdir": "ztest/model_keras/autokeras/"
        
        }
    },

"text":{

        "model_pars": {
            "model_name":"text",
            "model_pars":{
                            "num_classes":null,
                            "multi_label":false,
                            "loss":  null,
                            "metrics": null,
                            "name":"text_classifier",
                            "max_trials":10,
                            "directory": null,
                            "objective": "val_loss",
                            "overwrite":true,
                            "seed":  null
                            }
        },

        "data_pars" :{
            "dataset": "IMDB",
            "data_path": "dataset/nlp/",
            "num_words" : 1000,
            "validation_split":0.2
        },

        "compute_pars": {
            "epochs":2
           
        },

        "out_pars": {
            "checkpointdir": "ztest/model_keras/autokeras/"
        
        }
    },

"tabular_classifier":{

        "model_pars": {
            "model_name":"tabular_classifier",
            "model_pars":{
                            "num_classes": null,
                            "multi_label": false,
                            "loss":  null,
                            "metrics": null,
                            "name":"tabular_classifier",
                            "max_trials":10,
                            "directory": null,
                            "objective": "val_loss",
                            "overwrite":true,
                            "seed":  null
                            }
        },

        "data_pars" :{
            "dataset": "Titanic Survival Prediction",
            "train_data_path": "dataset/tabular/autokeras_titanic_train.csv",
            "test_data_path": "dataset/tabular/autokeras_titanic_eval.csv",
            "validation_split":0.2
        },

        "compute_pars": {
            "epochs":2
            
        },

        "out_pars": {
            "checkpointdir": "ztest/model_keras/autokeras/"
        
        }
    }

}
